<?xml version="1.0" encoding="utf-8"?>
<resources>
    <color name="colorPrimary">@*android:color/primary_material_dark</color>
    <color name="colorPrimaryDark">@*android:color/primary_dark_material_dark</color>
    <color name="colorAccent">@*android:color/accent_material_light</color>
    <color name="transparent">#00000000</color>

    <color name="divider_color">#00000000</color>
    <color name="underline_color">@*android:color/accent_material_light</color>
    <color name="indicator_color">@*android:color/accent_material_light</color>
    <color name="tab_text_color">#b3ffffff</color>

    <color name="navigation_drawer_background">@*android:color/holo_gray_bright</color>
    <color name="extension_list_item_color">@*android:color/accent_material_light</color>
    <color name="configure_light_background">#00000000</color>
    <color name="background_tab_pressed">@*android:color/accent_material_light</color>
    <color name="notification_background">@*android:color/background_material_dark</color>
    <color name="setting_separator">#00000000</color>

    <!-- Gesture Anywhere -->
    <color name="ga_gesture_color">@*android:color/accent_material_light</color>

    <color name="seekbar_dot_color">@*android:color/accent_material_light</color>

    <color name="floating_action_button_touch_tint">#80ffffff</color>
</resources>
